db_connection.py
db_discovery.py
execute_query.py
logging_config.py
mcp_postgresql_server.py
project_utils.py
mcp_postgresql_server-1.4.0.dist-info/licenses/LICENSE
mcp_postgresql_server-1.4.0.dist-info/METADATA
mcp_postgresql_server-1.4.0.dist-info/WHEEL
mcp_postgresql_server-1.4.0.dist-info/entry_points.txt
mcp_postgresql_server-1.4.0.dist-info/top_level.txt
mcp_postgresql_server-1.4.0.dist-info/RECORD
