Metadata-Version: 2.4
Name: mcp-postgresql-server
Version: 1.4.0
Summary: A secure, read-only PostgreSQL Model Context Protocol (MCP) server for AI assistant integration with automatic database discovery and connection management
Author: sebcbi1
Maintainer: sebcbi1
License-Expression: MIT
Project-URL: Homepage, https://github.com/sebcbi1/mcp-postgresql-server
Project-URL: Repository, https://github.com/sebcbi1/mcp-postgresql-server
Project-URL: Documentation, https://github.com/sebcbi1/mcp-postgresql-server/blob/main/README.md
Project-URL: Issues, https://github.com/sebcbi1/mcp-postgresql-server/issues
Keywords: mcp,postgresql,database,ai-assistant,claude,model-context-protocol,sql,postgres,database-tools
Classifier: Intended Audience :: Developers
Classifier: Programming Language :: Python :: 3
Classifier: Topic :: Database
Classifier: Topic :: Database :: Database Engines/Servers
Classifier: Topic :: Software Development :: Libraries :: Python Modules
Classifier: Topic :: Scientific/Engineering :: Artificial Intelligence
Classifier: Environment :: Console
Classifier: Operating System :: OS Independent
Requires-Python: >=3.13
License-File: LICENSE
Requires-Dist: mcp>=1.13.1
Requires-Dist: psycopg2-binary>=2.9.10
Requires-Dist: pydantic>=2.11.7
Requires-Dist: python-dotenv>=1.1.1
Requires-Dist: pyyaml>=6.0.2
Requires-Dist: toml>=0.10.2
Requires-Dist: typing-extensions>=4.15.0
Provides-Extra: dev
Requires-Dist: pytest>=7.0.0; extra == "dev"
Requires-Dist: pytest-asyncio>=0.21.0; extra == "dev"
Requires-Dist: black>=23.0.0; extra == "dev"
Requires-Dist: flake8>=6.0.0; extra == "dev"
Requires-Dist: mypy>=1.5.0; extra == "dev"
Requires-Dist: coverage>=7.0.0; extra == "dev"
Dynamic: license-file
